fs_email/__init__.py
fs_email/admin.py
fs_email/apps.py
fs_email/models.py
fs_email/locale/ru/LC_MESSAGES/django.mo
fs_email/locale/ru/LC_MESSAGES/django.po
fs_email/migrations/0001_initial.py
fs_email/migrations/0002_email.py
fs_email/migrations/__init__.py
django_fs_email-1.0.2.dist-info/LICENSE
django_fs_email-1.0.2.dist-info/METADATA
django_fs_email-1.0.2.dist-info/WHEEL
django_fs_email-1.0.2.dist-info/top_level.txt
django_fs_email-1.0.2.dist-info/RECORD
