Metadata-Version: 2.1
Name: django-fs-email
Version: 1.0.2
Summary: The Django-related reusable app provides the ability to send multipart emails and store them in a database.
Home-page: https://github.com/fogstream/django-fs-email
Author: Yuri Lya
Author-email: yuri.lya@fogstream.ru
License: The MIT License (MIT)
Platform: UNKNOWN
Classifier: Development Status :: 5 - Production/Stable
Classifier: Environment :: Web Environment
Classifier: Intended Audience :: Developers
Classifier: Operating System :: OS Independent
Classifier: Programming Language :: Python
Classifier: Framework :: Django
Requires-Python: >=3.6
Requires-Dist: html2text
